fedlearner/__init__.py
fedlearner/channel/__init__.py
fedlearner/channel/channel.py
fedlearner/channel/client_interceptor.py
fedlearner/channel/server_interceptor.py
fedlearner/common/__init__.py
fedlearner/common/argparse_util.py
fedlearner/common/common.py
fedlearner/common/db_client.py
fedlearner/common/dfs_client.py
fedlearner/common/etcd_client.py
fedlearner/common/leveldb.py
fedlearner/common/metrics.py
fedlearner/common/mock_kvstore.py
fedlearner/common/mysql_client.py
fedlearner/common/summary_hook.py
fedlearner/data_join/__init__.py
fedlearner/data_join/common.py
fedlearner/data_join/csv_dict_writer.py
fedlearner/data_join/data_block_dumper.py
fedlearner/data_join/data_block_manager.py
fedlearner/data_join/data_block_visitor.py
fedlearner/data_join/data_join_master.py
fedlearner/data_join/data_join_worker.py
fedlearner/data_join/data_portal_job_manager.py
fedlearner/data_join/data_portal_master.py
fedlearner/data_join/data_portal_worker.py
fedlearner/data_join/example_id_batch_fetcher.py
fedlearner/data_join/example_id_dumper.py
fedlearner/data_join/example_id_sync_follower.py
fedlearner/data_join/example_id_sync_leader.py
fedlearner/data_join/example_id_visitor.py
fedlearner/data_join/example_join_follower.py
fedlearner/data_join/example_join_leader.py
fedlearner/data_join/item_batch_seq_processor.py
fedlearner/data_join/negative_example_generator.py
fedlearner/data_join/raw_data_manifest_manager.py
fedlearner/data_join/raw_data_partitioner.py
fedlearner/data_join/raw_data_publisher.py
fedlearner/data_join/raw_data_visitor.py
fedlearner/data_join/routine_worker.py
fedlearner/data_join/sort_run_dumper.py
fedlearner/data_join/sort_run_merger.py
fedlearner/data_join/transmit_follower.py
fedlearner/data_join/transmit_leader.py
fedlearner/data_join/visitor.py
fedlearner/data_join/cmd/__init__.py
fedlearner/data_join/cmd/data_join_master_service.py
fedlearner/data_join/cmd/data_join_worker_service.py
fedlearner/data_join/cmd/data_portal_master_service.py
fedlearner_manylinux-1.5.dev20210429.dist-info/AUTHORS
fedlearner_manylinux-1.5.dev20210429.dist-info/LICENSE
fedlearner_manylinux-1.5.dev20210429.dist-info/METADATA
fedlearner_manylinux-1.5.dev20210429.dist-info/NOTICE
fedlearner_manylinux-1.5.dev20210429.dist-info/WHEEL
fedlearner_manylinux-1.5.dev20210429.dist-info/top_level.txt
fedlearner_manylinux-1.5.dev20210429.dist-info/RECORD
